sphinx_revealjs/__init__.py
sphinx_revealjs/builders.py
sphinx_revealjs/contexts.py
sphinx_revealjs/deprecated.py
sphinx_revealjs/directives.py
sphinx_revealjs/nodes.py
sphinx_revealjs/utils.py
sphinx_revealjs/writers.py
sphinx_revealjs/_ext/__init__.py
sphinx_revealjs/_ext/highlightings.py
sphinx_revealjs/_ext/notes.py
sphinx_revealjs/_static/.gitignore
sphinx_revealjs/_static/revealjs/LICENSE
sphinx_revealjs/_static/revealjs/css/layout.scss
sphinx_revealjs/_static/revealjs/css/reveal.scss
sphinx_revealjs/_static/revealjs/css/print/paper.scss
sphinx_revealjs/_static/revealjs/css/print/pdf.scss
sphinx_revealjs/_static/revealjs/css/theme/README.md
sphinx_revealjs/_static/revealjs/css/theme/source/beige.scss
sphinx_revealjs/_static/revealjs/css/theme/source/black-contrast.scss
sphinx_revealjs/_static/revealjs/css/theme/source/black.scss
sphinx_revealjs/_static/revealjs/css/theme/source/blood.scss
sphinx_revealjs/_static/revealjs/css/theme/source/dracula.scss
sphinx_revealjs/_static/revealjs/css/theme/source/league.scss
sphinx_revealjs/_static/revealjs/css/theme/source/moon.scss
sphinx_revealjs/_static/revealjs/css/theme/source/night.scss
sphinx_revealjs/_static/revealjs/css/theme/source/serif.scss
sphinx_revealjs/_static/revealjs/css/theme/source/simple.scss
sphinx_revealjs/_static/revealjs/css/theme/source/sky.scss
sphinx_revealjs/_static/revealjs/css/theme/source/solarized.scss
sphinx_revealjs/_static/revealjs/css/theme/source/white-contrast.scss
sphinx_revealjs/_static/revealjs/css/theme/source/white.scss
sphinx_revealjs/_static/revealjs/css/theme/template/exposer.scss
sphinx_revealjs/_static/revealjs/css/theme/template/mixins.scss
sphinx_revealjs/_static/revealjs/css/theme/template/settings.scss
sphinx_revealjs/_static/revealjs/css/theme/template/theme.scss
sphinx_revealjs/_static/revealjs/dist/reset.css
sphinx_revealjs/_static/revealjs/dist/reveal.css
sphinx_revealjs/_static/revealjs/dist/reveal.esm.js
sphinx_revealjs/_static/revealjs/dist/reveal.esm.js.map
sphinx_revealjs-3.2.1.dist-info/licenses/LICENSE
sphinx_revealjs-3.2.1.dist-info/WHEEL
sphinx_revealjs-3.2.1.dist-info/METADATA
sphinx_revealjs-3.2.1.dist-info/RECORD
