Metadata-Version: 2.4
Name: sphinx-revealjs
Version: 3.2.1
Summary: Sphinx extension with theme to generate Reveal.js presentation
Author-email: Kazuya Takei <myself@attakei.net>
Requires-Python: >= 3.9
Classifier: Development Status :: 5 - Production/Stable
Classifier: Environment :: Console
Classifier: Environment :: Web Environment
Classifier: Framework :: Sphinx
Classifier: Framework :: Sphinx :: Extension
Classifier: Framework :: Sphinx :: Theme
Classifier: Intended Audience :: Developers
Classifier: License :: OSI Approved :: Apache Software License
Classifier: Operating System :: OS Independent
Classifier: Programming Language :: Python
Classifier: Programming Language :: Python :: 3
Classifier: Programming Language :: Python :: 3 :: Only
Classifier: Programming Language :: Python :: 3.9
Classifier: Programming Language :: Python :: 3.10
Classifier: Programming Language :: Python :: 3.11
Classifier: Programming Language :: Python :: 3.12
Classifier: Programming Language :: Python :: 3.13
Classifier: Topic :: Documentation :: Sphinx
Classifier: Topic :: Internet :: WWW/HTTP :: Site Management
Classifier: Topic :: Multimedia :: Graphics :: Presentation
Classifier: Topic :: Software Development
Classifier: Topic :: Software Development :: Documentation
Classifier: Topic :: Text Processing :: Markup :: HTML
License-File: LICENSE
Requires-Dist: docutils
Requires-Dist: Sphinx>=7
Requires-Dist: packaging
Requires-Dist: playwright ; extra == "screenshot"
Project-URL: Documentation, https://sphinx-revealjs.readthedocs.io/
Project-URL: Home, https://attakei.github.io/sphinx-revealjs
Project-URL: Repository, https://github.com/attakei/sphinx-revealjs
Provides-Extra: screenshot
